anvil/__init__.py
anvil/app.py
anvil/config/__init__.py
anvil/config/models.py
anvil/config/settings.py
anvil/screens/__init__.py
anvil/screens/agent_edit.py
anvil/screens/auth.py
anvil/screens/foundry_select.py
anvil/screens/home.py
anvil/screens/project_select.py
anvil/screens/splash.py
anvil/screens/subscription_select.py
anvil/services/__init__.py
anvil/services/arm_client.py
anvil/services/auth.py
anvil/services/exceptions.py
anvil/services/foundry.py
anvil/services/project_client.py
anvil/services/subscriptions.py
anvil/styles/app.tcss
anvil/widgets/__init__.py
anvil/widgets/searchable_list.py
anvil/widgets/sidebar.py
anvil_tui-0.1.3.dist-info/METADATA
anvil_tui-0.1.3.dist-info/WHEEL
anvil_tui-0.1.3.dist-info/entry_points.txt
anvil_tui-0.1.3.dist-info/licenses/LICENSE
anvil_tui-0.1.3.dist-info/RECORD
